cmvrt/__init__.py
cmvrt/sgConvertor.py
cmvrt/sgdConvertor.py
cnvrt/__init__.py
cnvrt/sgdConvertor.py
dwnld/__init__.py
dwnld/downloader.py
cmvrt-0.0.2.dist-info/METADATA
cmvrt-0.0.2.dist-info/WHEEL
cmvrt-0.0.2.dist-info/top_level.txt
cmvrt-0.0.2.dist-info/RECORD
